sigfoxapi_fork/__init__.py
sigfoxapi_fork/requesthandler.py
sigfoxapi_fork-0.3.3.dist-info/LICENSE
sigfoxapi_fork-0.3.3.dist-info/METADATA
sigfoxapi_fork-0.3.3.dist-info/WHEEL
sigfoxapi_fork-0.3.3.dist-info/top_level.txt
sigfoxapi_fork-0.3.3.dist-info/RECORD
