Metadata-Version: 2.1
Name: sigfoxapi-fork
Version: 0.3.3
Summary: Python wrapper for the Sigfox backend REST API
Home-page: https://github.com/KanduTeam/python-sigfox-backend-api.git
Author: Pierre-Aymeric MASSE
Author-email: cto@kandu.fr
License: BSD 2-clause "Simplified" License
Keywords: sigfox
Platform: UNKNOWN
Classifier: Development Status :: 4 - Beta
Classifier: Intended Audience :: Developers
Classifier: License :: OSI Approved :: BSD License
Classifier: Programming Language :: Python :: 3
Requires-Dist: drest (==0.9.12)
